app/__init__.py
app/run.py
base/__init__.py
base/base.py
base/registry.py
core/__init__.py
core/orchestrator.py
depanalyzer/__init__.py
depanalyzer/utils/__init__.py
depanalyzer/utils/graph.py
dependencies/__init__.py
dependencies/dependency_manager.py
parsers/__init__.py
parsers/cpp/__init__.py
parsers/cpp/code_parser.py
parsers/cpp/config_parser.py
parsers/cpp/todo
parsers/hvigor/__init__.py
parsers/hvigor/code_parser.py
parsers/hvigor/config_parser.py
tasks/__init__.py
tasks/enhanced_task_builder.py
tasks/parse_types.py
tasks/task_system.py
utils/__init__.py
utils/fs.py
utils/graph.py
utils/scaffold.py
utils/structure.py
depanalyzer-0.1.2.dist-info/METADATA
depanalyzer-0.1.2.dist-info/WHEEL
depanalyzer-0.1.2.dist-info/entry_points.txt
depanalyzer-0.1.2.dist-info/RECORD
