Metadata-Version: 2.3
Name: depanalyzer
Version: 0.1.2
Summary: Dependency analyzer tool
License: MIT
Author: Zihao
Author-email: zhangzihao2025@lzu.edu.cn> Shufei <2337739735@qq.com
Requires-Python: >=3.12,<=3.14
Classifier: License :: OSI Approved :: MIT License
Classifier: Programming Language :: Python :: 3
Classifier: Programming Language :: Python :: 3.12
Classifier: Programming Language :: Python :: 3.13
Requires-Dist: json5 (>=0.12.0,<0.13.0)
Requires-Dist: lark
Requires-Dist: liscopelens (>=0.2.15,<0.3.0)
Requires-Dist: networkx (>=3.2.1,<4.0.0)
Requires-Dist: platformdirs (>=4.0.0,<5.0.0)
Requires-Dist: pydantic (>=2.11.7,<3.0.0)
Requires-Dist: requests (>=2.31.0,<3.0.0)
Requires-Dist: rich (>=14.0.0,<15.0.0)
Requires-Dist: textual (>=3.0.1,<4.0.0)
Requires-Dist: toml (>=0.10.2,<0.11.0)
Requires-Dist: tree-sitter
Requires-Dist: tree-sitter-c
Requires-Dist: tree-sitter-cpp (>=0.23.4,<0.24.0)
Requires-Dist: tree-sitter-typescript
